markdown_captions/__init__.py
markdown_captions/markdown_captions.py
markdown_captions-2.1.1.dist-info/METADATA
markdown_captions-2.1.1.dist-info/WHEEL
markdown_captions-2.1.1.dist-info/top_level.txt
markdown_captions-2.1.1.dist-info/RECORD
