Metadata-Version: 2.1
Name: markdown-captions
Version: 2.1.1
Summary: Turn markdown images into captioned images using <figure>
Home-page: https://github.com/Evidlo/markdown_captions
Author: evidlo
Author-email: evan@evanw.org
License: GPL3
Keywords: markdown figures captions subtitles
Platform: UNKNOWN
Classifier: Development Status :: 4 - Beta
Classifier: Intended Audience :: Developers
Classifier: License :: OSI Approved :: GNU General Public License v3 (GPLv3)
Classifier: Operating System :: OS Independent
Classifier: Programming Language :: Python
Classifier: Topic :: Text Processing :: Markup :: HTML
Requires-Dist: Markdown (>=3.0.1)
